idq/__init__.py
idq/example.py
idq/helpers.py
idq/harness/__init__.py
idq/harness/static/harness.css
idq/harness/templates/apidocs.html
idq/harness/templates/base.html
idq/harness/templates/batch.html
idq/harness/templates/home.html
idq/harness/templates/single.html
idq-0.6.0.dist-info/DESCRIPTION.rst
idq-0.6.0.dist-info/METADATA
idq-0.6.0.dist-info/RECORD
idq-0.6.0.dist-info/WHEEL
idq-0.6.0.dist-info/metadata.json
idq-0.6.0.dist-info/top_level.txt
