Metadata-Version: 2.0
Name: idq
Version: 0.6.0
Summary: iDigQuality Base Module
Home-page: http://github.com/idigbio/idq/
Author: Alex Thompson
Author-email: godfoder@acis.ufl.edu
License: MIT
Platform: UNKNOWN
Classifier: Development Status :: 5 - Production/Stable
Classifier: Intended Audience :: Developers
Classifier: Natural Language :: English
Classifier: License :: OSI Approved :: MIT License
Classifier: Operating System :: OS Independent
Classifier: Programming Language :: Python
Classifier: Programming Language :: Python :: 2
Classifier: Programming Language :: Python :: 2.6
Classifier: Programming Language :: Python :: 2.7
Classifier: Topic :: Software Development :: Libraries :: Python Modules
Requires-Dist: flask
Requires-Dist: flask-bootstrap
Requires-Dist: flask-nav
Requires-Dist: flask-wtf
Requires-Dist: unicodecsv
